{
    "family": "airflow-demo-webserver", 
    "taskRoleArn": "", 
    "executionRoleArn": "", 
    "networkMode": "awsvpc", 
    "containerDefinitions": [
        {
            "name": "webserver", 
            "image": "", 
            "cpu": 0, 
            "memory": 512, 
            "memoryReservation": 256, 
            "portMappings": [
                {
                    "containerPort": 8080, 
                    "hostPort": 8080, 
                    "protocol": "tcp"
                }
            ], 
            "essential": true, 
            "command": [
                "webserver"
            ], 
            "environment": [
                {
                    "name": "EXECUTOR", 
                    "value": "Celery"
                }
            ], 
            "mountPoints": [
                {
                    "sourceVolume": "dags", 
                    "containerPath": "/usr/local/airflow/dags", 
                    "readOnly": true
                }
            ], 
            "logConfiguration": {
                "logDriver": "awslogs", 
                "options": {
                    "awslogs-group": "/ecs/airflow-demo-webserver",
                    "awslogs-region": "ap-southeast-2",
                    "awslogs-stream-prefix": "ecs"                
                }
            }
        },
        {
            "name": "git-sync", 
            "image": "", 
            "cpu": 0, 
            "memory": 256, 
            "memoryReservation": 128, 
            "essential": true, 
            "environment": [
                {
                    "name": "GIT_SYNC_BRANCH",
                    "value": "testing"
                },
                {
                    "name": "GIT_SYNC_DEST",
                    "value": "/git"
                },
                {
                    "name": "GIT_SYNC_REPO",
                    "value": "https://github.com/jeevanullas/airflow-sample-dags.git"
                },
                {
                    "name": "GIT_SYNC_REV",
                    "value": "FETCH_HEAD"
                },
                {
                    "name": "GIT_SYNC_WAIT",
                    "value": "10"
                }
            ], 
            "mountPoints": [
                {
                    "sourceVolume": "dags", 
                    "containerPath": "/git", 
                    "readOnly": false
                }
            ], 
            "logConfiguration": {
                "logDriver": "awslogs", 
                "options": {
                    "awslogs-group": "/ecs/airflow-demo-webserver",
                    "awslogs-region": "ap-southeast-2",
                    "awslogs-stream-prefix": "ecs"                
                }
            }
        }
    ], 
    "volumes": [
        {
          "name": "dags"
        }
    ],
    "requiresCompatibilities": [
        "FARGATE"
    ], 
    "cpu": "512", 
    "memory": "1024"
}
